{"schemaVersion":"1.0","appDefinitionTemplate":{"id":"/providers/Microsoft.PowerApps/apps/","type":"Microsoft.PowerApps/apps","tags":{"primaryDeviceWidth":"640","primaryDeviceHeight":"1136","supportsPortrait":"true","supportsLandscape":"true","primaryFormFactor":"Phone","publisherVersion":"3.22111.19","minimumRequiredApiVersion":"2.2.0","hasComponent":"false","hasUnlockedComponent":"false","isUnifiedRootApp":"false","sienaVersion":"20221127T011144Z-3.22111.19.0"},"properties":{"appVersion":"2022-11-27T01:11:44Z","lifeCycleId":"Published","createdByClientVersion":{"major":3,"minor":22111,"build":19,"revision":0,"majorRevision":0,"minorRevision":0},"minClientVersion":{"major":3,"minor":22111,"build":19,"revision":0,"majorRevision":0,"minorRevision":0},"backgroundColor":"RGBA(0,176,240,1)","backgroundImageUri":"/1799602033187719703/N80f253fa-6213-4660-a1c7-d8f1bbea691d-logoSmallFile","displayName":"AplicaciónU","description":"","commitMessage":"","appUris":{"documentUri":{"value":"/1799602033187719703/N0a345941-cea0-4d93-b6db-b1bfd9551017-document.msapp"},"imageUris":[],"additionalUris":[]},"createdTime":"0001-01-01T00:00:00Z","lastModifiedTime":"0001-01-01T00:00:00Z","sharedGroupsCount":0,"sharedUsersCount":0,"icons":{"smallIconUri":"/1799602033187719703/N268ec49e-b704-4a7e-8c85-0d0466d50265-small.png","mediumIconUri":"/1799602033187719703/N3bb0a607-b3bf-4323-9c67-405ab450c09d-medium.png","largeIconUri":"/1799602033187719703/Na5609e4d-8356-4ac4-b858-f78f5e83b9d2-large.png","wideIconUri":"/1799602033187719703/N7bb2d2d5-f74c-4e4b-bdb6-ac2428b90a0d-wide.png"},"connectionReferences":{"df9227cf-6666-4233-85db-e36e85ddbc95":{"id":"835bb3d0-7905-4b44-abc4-6ad00de530a6","displayName":"Hojas de cálculo de Google","iconUri":"https://connectoricons-prod.azureedge.net/releases/v1.0.1590/1.0.1590.2954/googlesheet/icon.png","dataSources":["Hoja1"],"dependencies":[],"dependents":[],"parameterHints":{},"parameterHintsV2":{},"isOnPremiseConnection":false,"dataSets":{"18ixK-KrW2RwXe6JtLRXpx_A4UQaK5DeM86Le0AFQ5yk":{"dataSources":{"Hoja1":{"tableName":"1641597147"}}}},"apiTier":"Standard","isCustomApiConnection":false,"actions":["providers/PowerPlatform.Governance/Operations/Read","providers/PowerPlatform.Governance/Operations/Write","providers/PowerPlatform.Governance/Operations/Delete"]}},"databaseReferences":{},"almMode":"Environment","performanceOptimizationEnabled":true,"canConsumeAppPass":true,"enableModernRuntimeMode":false,"executionRestrictions":{"isTeamsOnly":false,"dataLossPreventionEvaluationResult":{"status":"Compliant","lastEvaluationDate":"2022-11-27T01:11:49.3102274Z","violations":[],"violationsByPolicy":[],"violationErrorMessage":"La aplicación usa los siguientes conectores: shared_googlesheet."}}},"appType":"ClassicCanvasApp","appComponents":[]}}